Workbook

Sheet Read me
A1: Problem survey kit: prove to investors the problem is real
A2: Use these five tabs in order: Questionnaire, Sampling plan, Responses, Analysis. Interview guide supports the depth calls.
A4: What this is | B4: A 9-minute questionnaire, a sampling plan, a responses sheet and an analysis sheet. Each question tests a numbered hypothesis (H1 to H12). The Analysis sheet shows whether each hypothesis is supported and writes a ready-to-use sentence for the deck.
A5: Step 1 | B5: Copy the Questionnaire into Google Forms or Typeform. Keep the answer wording exactly as written. Add the consent text at the end of the Questionnaire sheet before question A1.
A6: Step 2 | B6: Pilot it with 5 people. Time it. Fix anything unclear.
A7: Step 3 | B7: Use the Sampling plan to reach 300+ answers (about half from overseas). Track answers by segment weekly.
A8: Step 4 | B8: Export responses as CSV. Paste into the Responses sheet from row 7. Match columns by their Q code. Row 6 is only an example.
A9: Step 5 | B9: Open Analysis. Read the verdicts, the step ranking and the generated statements. Put the 5 strongest statements and 5 quotes in the deck (slide numbers are on each row).
A10: Thresholds | B10: The "pass if at least" numbers are suggestions. Agree them with your advisors before you look at the results.
A11: Limits | B11: This is a convenience sample. Say so on the slide. It shows the pain is real and common among people you reached, not a census of the UAE. Concept-test answers (F and G) show interest, not future behaviour.
A12: Compliance | B12: Section G tests interest in a referral fee. Do not promise payments to unlicensed people until your legal opinion confirms a lawful structure. Do not collect contact details without the consent screen.
A13: Data entry notes | B13: Questions B4 and C3 have commas in their answers, so they have no dropdown in Responses. Paste the exact wording. Multi-choice and open-text questions (B1, B11, C1, C4, E1, E2 and others) are read manually; tag themes in a separate sheet or tool.
A14: Colour code | B14: Blue text = input you can change. Yellow fill = cells to fill in. Grey italic = example, not counted.

Sheet Questionnaire
A1: Questionnaire (about 9 minutes)
A2: Copy each row into Google Forms or Typeform. Keep the option wording exactly so the Responses and Analysis sheets keep working. Multi-choice and open-text questions are read manually.
A4: Q | B4: Section | C4: Question text | D4: Answer type | E4: Answer options (in order) | F4: Required | G4: Show if | H4: Tests | I4: Deck slide | J4: Responses column
A5: A1 | B5: A. About you | C5: Which best describes you? | D5: Single choice | E5: I bought property in the UAE in the last 3 years | I own UAE property as an investment | I plan to buy UAE property in the next 12 months | I rent in the UAE | I plan to rent in the UAE in the next 12 months | I work in UAE real estate (agent, broker, developer) | None of these | F5: Yes | G5: Always | H5: Screener | I5: 3 | J5: A1
A6: A2 | B6: A. About you | C6: Where do you live now? | D6: Single choice | E6: In the UAE | Outside the UAE | F6: Yes | G6: A1 is not "None of these" | H6: Segment cut | I6: 3 | J6: A2
A7: A3 | B7: A. About you | C7: Which country do you live in? | D7: Dropdown (countries) | F7: No | G7: A2 = Outside the UAE | H7: Segment cut | I7: 3 | J7: -
A8: A4 | B8: A. About you | C8: Your age band | D8: Single choice | E8: 18-24 | 25-34 | 35-44 | 45-54 | 55 or over | F8: No | G8: Always | H8: Profile | I8: 3 | J8: -
A9: A5 | B9: A. About you | C9: What is your typical budget for buying a property? | D9: Single choice | E9: Under AED 500k | AED 500k-1m | AED 1m-2m | AED 2m-5m | Over AED 5m | Not sure | F9: Yes | G9: A1 is a buyer or investor | H9: Profile | I9: 3 | J9: A5
A10: A6 | B10: A. About you | C10: What is your typical yearly rent budget? | D10: Single choice | E10: Under AED 60k | AED 60k-120k | AED 120k-250k | Over AED 250k | Not sure | F10: Yes | G10: A1 is a renter | H10: Profile | I10: 3 | J10: -
A11: A7 | B11: A. About you | C11: What is the main purpose? | D11: Single choice | E11: Live in it | Rental income or investment | Both | Holiday home | F11: No | G11: A1 is a buyer or investor | H11: Profile | I11: 3 | J11: -
A12: B1 | B12: B. Your property journey | C12: Where did you start your search? (pick all that apply) | D12: Multi choice | E12: Property portal | Developer website | Agent or broker | Friends and family | Social media or YouTube | Search engine or AI chat | Other | F12: No | G12: A1 is not a professional | H12: Context | I12: 2 | J12: -
A13: B2 | B13: B. Your property journey | C13: How many different websites, apps or people did you use before deciding? | D13: Single choice | E13: 1-2 | 3-5 | 6-10 | More than 10 | F13: No | G13: A1 is not a professional | H13: Context | I13: 2 | J13: -
A14: B3a | B14: B. Your property journey | C14: How difficult was this step: Finding reliable information on prices and areas? (1 = very easy, 5 = very difficult, N/A allowed) | D14: Rating 1-5 (matrix row) | E14: 1 | 2 | 3 | 4 | 5 | N/A | F14: No | G14: A1 is not a professional | H14: H1, H4 and step ranking | I14: 2 | J14: B3a
A15: B3b | B15: B. Your property journey | C15: How difficult was this step: Comparing options fairly? (1 = very easy, 5 = very difficult, N/A allowed) | D15: Rating 1-5 (matrix row) | E15: 1 | 2 | 3 | 4 | 5 | N/A | F15: No | G15: A1 is not a professional | H15: H1, H4 and step ranking | I15: 2 | J15: B3b
A16: B3c | B16: B. Your property journey | C16: How difficult was this step: Checking that a listing, developer or seller is genuine? (1 = very easy, 5 = very difficult, N/A allowed) | D16: Rating 1-5 (matrix row) | E16: 1 | 2 | 3 | 4 | 5 | N/A | F16: No | G16: A1 is not a professional | H16: H1, H4 and step ranking | I16: 2 | J16: B3c
A17: B3d | B17: B. Your property journey | C17: How difficult was this step: Understanding the total cost including fees? (1 = very easy, 5 = very difficult, N/A allowed) | D17: Rating 1-5 (matrix row) | E17: 1 | 2 | 3 | 4 | 5 | N/A | F17: No | G17: A1 is not a professional | H17: H1, H4 and step ranking | I17: 2 | J17: B3d
A18: B3e | B18: B. Your property journey | C18: How difficult was this step: Paperwork and government registrations? (1 = very easy, 5 = very difficult, N/A allowed) | D18: Rating 1-5 (matrix row) | E18: 1 | 2 | 3 | 4 | 5 | N/A | F18: No | G18: A1 is not a professional | H18: H1, H4 and step ranking | I18: 2 | J18: B3e
A19: B3f | B19: B. Your property journey | C19: How difficult was this step: Arranging finance or payment? (1 = very easy, 5 = very difficult, N/A allowed) | D19: Rating 1-5 (matrix row) | E19: 1 | 2 | 3 | 4 | 5 | N/A | F19: No | G19: A1 is not a professional | H19: H1, H4 and step ranking | I19: 2 | J19: B3f
... A24: B5 | B24: B. Your property journey | C24: Did you face costs you did not expect (fees, charges, service charges)? | D24: Single choice | E24: Yes | No | Not sure | F24: Yes | G24: A1 is not a professional | H24: H3 | I24: 2 | J24: B5
A25: B6 | B25: B. Your property journey | C25: From first search to keys or title deed, about how many weeks did it take? (enter a number) | D25: Number | F25: No | G25: A1 is a past buyer or renter | H25: Context | I25: 2 | J25: B6
A26: B7 | B26: B. Your property journey | C26: How confident were you that the price or rent you agreed was fair? (1 = not at all, 5 = completely) | D26: Rating 1-5 | E26: 1 | 2 | 3 | 4 | 5 | F26: No | G26: A1 is not a professional | H26: H12 | I26: 2 | J26: B7
A27: B8 | B27: B. Your property journey | C27: Did you use an agent? | D27: Single choice | E27: Yes | No | F27: No | G27: A1 is not a professional | H27: Context | I27: 2 | J27: -
A28: B9 | B28: B. Your property journey | C28: How satisfied were you with your agent? (1 = very unhappy, 5 = very happy) | D28: Rating 1-5 | E28: 1 | 2 | 3 | 4 | 5 | F28: No | G28: B8 = Yes | H28: Context | I28: 2 | J28: B9
A29: B10 | B29: B. Your property journey | C29: Have you ever delayed or given up on buying or renting because it felt too complicated or risky? | D29: Single choice | E29: Yes | No | Not sure | F29: No | G29: A1 is not a professional | H29: H4 | I29: 2 | J29: B10
A30: B11 | B30: B. Your property journey | C30: What was the single biggest frustration? (your words) | D30: Open text | F30: No | G30: A1 is not a professional | H30: Quotes | I30: 2 | J30: -
A31: B12 | B31: B. Your property journey | C31: What do you wish someone had told you before you started? | D31: Open text | F31: No | G31: A1 is not a professional | H31: Quotes | I31: 2 | J31: -
A32: C1 | B32: C. Information and insights | C32: Which information would help you decide most? (pick up to 3) | D32: Multi choice (max 3) | E32: Price trends by area | Rental yield | Developer delivery record | Service charges | Supply pipeline in the area | How easily I can resell | Mortgage affordability | Neighbourhood quality | F32: No | G32: A1 is not a professional | H32: Insights design | I32: 6 | J32: -
A33: C2 | B33: C. Information and insights | C33: How much do you trust the information on property portals? (1 = not at all, 5 = completely) | D33: Rating 1-5 | E33: 1 | 2 | 3 | 4 | 5 | F33: No | G33: A1 is not a professional | H33: H11 | I33: 2 | J33: C2
A34: C3 | B34: C. Information and insights | C34: Would you pay for independent insights such as price trends, yield and developer delivery record? | D34: Single choice | E34: No, only if free | Yes, one-off up to AED 50 | Yes, one-off AED 50-150 | Yes, one-off AED 150-500 | Yes, monthly subscription | F34: Yes | G34: A1 is not a professional | H34: H6 | I34: 7 | J34: C3
A35: C4 | B35: C. Information and insights | C35: How do you decide today whether a deal is good? (your words) | D35: Open text | F35: No | G35: A1 is not a professional | H35: Quotes | I35: 2 | J35: -
A36: D1 | B36: D. 3D view and designing the home | C36: How important is a 3D walkthrough of the exact unit before you buy or rent? (1 = not important, 5 = essential) | D36: Rating 1-5 | E36: 1 | 2 | 3 | 4 | 5 | F36: Yes | G36: A1 is not a professional | H36: H7 | I36: 6 | J36: D1
A37: D2 | B37: D. 3D view and designing the home | C37: Would a 3D walkthrough make you comfortable reserving without visiting in person? | D37: Single choice | E37: Yes | Maybe | No | F37: Yes | G37: A1 is not a professional | H37: H7 | I37: 6 | J37: D2
A38: D3 | B38: D. 3D view and designing the home | C38: After buying or renting, how interested would you be in designing and furnishing the home virtually first? (1 = not at all, 5 = very) | D38: Rating 1-5 | E38: 1 | 2 | 3 | 4 | 5 | F38: No | G38: A1 is not a professional | H38: H10 | I38: 7 | J38: D3
A39: D4 | B39: D. 3D view and designing the home | C39: Would you buy furniture through the same app? | D39: Single choice | E39: Definitely | Probably | Not sure | Probably not | Definitely not | F39: Yes | G39: A1 is not a professional | H39: H10 | I39: 7 | J39: D4
A40: D5 | B40: D. 3D view and designing the home | C40: Would you book an interior designer through the same app? | D40: Single choice | E40: Definitely | Probably | Not sure | Probably not | Definitely not | F40: No | G40: A1 is not a professional | H40: H10 | I40: 7 | J40: D5
A41: D6 | B41: D. 3D view and designing the home | C41: What budget do you set for furnishing and design? | D41: Single choice | E41: Under AED 20k | AED 20k-50k | AED 50k-100k | AED 100k-250k | Over AED 250k | Not planning to | F41: No | G41: A1 is not a professional | H41: Sizing | I41: 8 | J41: -
A42: D7 | B42: D. 3D view and designing the home | C42: What is hardest about furnishing or designing a home here? (your words) | D42: Open text | F42: No | G42: A1 is not a professional | H42: Quotes | I42: 2 | J42: -
A43: E1 | B43: E. Documents, registrations and payments | C43: Which of these did you handle yourself or through an agent? (pick all that apply) | D43: Multi choice | E43: DLD or Oqood registration | Title deed | Ejari | DEWA setup | Mortgage paperwork | Service charge setup | Instalment tracking | Visa or Golden Visa | Insurance | F43: No | G43: A1 is not a professional | H43: H4 | I43: 2 | J43: -
A44: E2 | B44: E. Documents, registrations and payments | C44: How do you track instalments and deadlines today? (pick all that apply) | D44: Multi choice | E44: Spreadsheet | Agent reminders | Developer portal | Bank | Phone calendar | Memory | I do not track | F44: No | G44: A1 is not a professional | H44: H5 | I44: 2 | J44: -
A45: E3 | B45: E. Documents, registrations and payments | C45: Have you ever missed or been late on a payment, registration or document deadline? | D45: Single choice | E45: Yes | No | Not sure | F45: Yes | G45: A1 is not a professional | H45: H5a | I45: 2 | J45: E3
A46: E4 | B46: E. Documents, registrations and payments | C46: How useful would one dashboard be for all documents, registrations and payment reminders? (1 = not useful, 5 = very useful) | D46: Rating 1-5 | E46: 1 | 2 | 3 | 4 | 5 | F46: Yes | G46: A1 is not a professional | H46: H5b | I46: 6 | J46: E4
A47: E5 | B47: E. Documents, registrations and payments | C47: How comfortable would you be letting a licensed company handle registrations for you? (1 = not at all, 5 = fully) | D47: Rating 1-5 | E47: 1 | 2 | 3 | 4 | 5 | F47: No | G47: A1 is not a professional | H47: Trust | I47: 12 | J47: E5
A48: F1 | B48: F. The idea | C48: Idea: one app and one licensed company that helps you research with verified data, view the exact unit in 3D, reserve or rent online, then handles documents, registrations and payment reminders. Buying off-plan costs you no extra fee (the developer pays). On resale you see one clear fee upfront. How likely would you be to use it? (1 = never, 5 = definitely) | D48: Rating 1-5 | E48: 1 | 2 | 3 | 4 | 5 | F48: Yes | G48: A1 is not a professional | H48: H8 | I48: 5 | J48: F1
A49: F2 | B49: F. The idea | C49: What would stop you? (pick all that apply) | D49: Multi choice | E49: Trust in a new company | Fees | I prefer a human agent | Data privacy | Not seeing the property in person | Payment security | Nothing | Other | F49: No | G49: Always | H49: Objections | I49: 10 | J49: -
A50: F3 | B50: F. The idea | C50: For a full-service resale purchase, what fee would you accept? | D50: Single choice | E50: 0% (only if free) | Up to 0.5% | 0.5-1% | 1-2% | More than 2% | F50: No | G50: A1 is a buyer or investor | H50: Pricing | I50: 7 | J50: F3
A51: F4 | B51: F. The idea | C51: Which one feature matters most? | D51: Single choice | E51: Verified listings | Independent insights | 3D view | Document and payment tracker | Designer and furniture | Lowest fees | F51: No | G51: Always | H51: Priorities | I51: 6 | J51: -
A52: F5 | B52: F. The idea | C52: Would you like early access? | D52: Single choice | E52: Yes | No | F52: Yes | G52: Always | H52: Waitlist | I52: 9 | J52: F5
A53: F6 | B53: F. The idea | C53: If yes, your email or WhatsApp (optional, used only to contact you about early access) | D53: Short text | F53: No | G53: F5 = Yes | H53: Waitlist | I53: 9 | J53: -
A54: G1 | B54: G. Introducing friends (UAE residents) | C54: In the last 12 months, how many people asked you for advice on buying or renting property? | D54: Single choice | E54: 0 | 1-2 | 3-5 | 6 or more | F54: No | G54: A2 = In the UAE | H54: H9 | I54: 10 | J54: G1
A55: G2 | B55: G. Introducing friends (UAE residents) | C55: Have you ever introduced someone to an agent or developer? | D55: Single choice | E55: Yes | No | F55: No | G55: A2 = In the UAE | H55: H9 | I55: 10 | J55: -
A56: G3 | B56: G. Introducing friends (UAE residents) | C56: Concept test only: no payment is promised or offered. If you could earn a fee for introducing a buyer to a licensed brokerage, how likely would you be to do it? (1 = never, 5 = definitely) | D56: Rating 1-5 | E56: 1 | 2 | 3 | 4 | 5 | F56: No | G56: A2 = In the UAE | H56: H9 | I56: 10 | J56: G3
A57: G4 | B57: G. Introducing friends (UAE residents) | C57: What would motivate you most? (pick all that apply) | D57: Multi choice | E57: Cash reward | Share of commission | Guaranteed payout time | Recognition | Nothing | F57: No | G57: A2 = In the UAE | H57: H9 | I57: 10 | J57: -
A58: G5 | B58: G. Introducing friends (UAE residents) | C58: What concerns would you have? (pick all that apply) | D58: Multi choice | E58: Legal or licence rules | Trust in the company | Paperwork | Time | Risk to my reputation | F58: No | G58: A2 = In the UAE | H58: H9 | I58: 10 | J58: -
A59: G6 | B59: G. Introducing friends (UAE residents) | C59: Would you consider getting a RERA broker licence if the company sponsored your training? | D59: Single choice | E59: Yes | Maybe | No | F59: No | G59: A2 = In the UAE | H59: H9 | I59: 10 | J59: G6
A60: H1 | B60: H. Close | C60: Can we contact you for a 30-minute interview? | D60: Single choice | E60: Yes | No | F60: No | G60: Always | H60: Interviews | I60: - | J60: H2
C62: Consent screen (show before Q A1)
C63: This survey is anonymous unless you choose to share contact details. We use answers only to understand how people buy and rent property in the UAE. Data is stored securely, is not sold, and you can ask us to delete it at any time. By continuing you agree. (Have a UAE lawyer confirm this wording under the UAE personal data protection law before launch.)
C65: Question design rules applied: one idea per question, neutral wording, 1-5 scales labelled at both ends, "N/A" allowed, no promise of payment in the referral section, concept described the same way to everyone.

Sheet Sampling plan
A1: Sampling plan
A2: Who to ask, how many, and where. A convenience sample is fine for a pre-seed pitch if you say so. Do not claim it represents all of the UAE.
A4: Segment | B4: Target answers | C4: Minimum for a segment claim | D4: Where to find them | E4: Incentive (suggested) | F4: Owner
A5: Overseas people planning to buy in the UAE | B5: 120 | C5: 50 | D5: LinkedIn and Facebook groups for NRIs, UK and Pakistani expats; Reddit property threads; WhatsApp communities; ads targeted by country | E5: Prize draw (AED 500 voucher) | F5: Head of Growth
A6: UAE residents who bought or invest in the last 3 years | B6: 100 | C6: 50 | D6: Resident Facebook and WhatsApp groups, LinkedIn, personal network, developer owner groups | E6: Prize draw | F6: Head of Growth
A7: UAE renters and planning to rent | B7: 80 | C7: 40 | D7: Community groups, office HR networks, universities | E7: Prize draw | F7: Head of Growth
A8: Real estate professionals (agents, brokers, developers) | B8: 40 | C8: 20 | D8: LinkedIn, Trakheesi broker network, events. Only complete section G and H | E8: None | F8: Partnerships Lead
A9: Total target | B9: =SUM(B5:B8) -> 340
A11: Margin of error calculator
A12: Number of answers | B12: 300
A13: Margin of error (95% confidence, worst case) | B13: =1.96*SQRT(0.25/B12) -> 0.056580326 | C13: Example: 300 answers gives about +/-5.7%.
A15: Bias controls
A16: Do not send the survey only to friends; cap any single source at 30% of answers.
A17: Ask about past behaviour first (Section B) and the idea last (Section F), so the idea does not colour earlier answers.
A18: Describe the concept the same way to every respondent.
A19: Remove duplicate and incomplete answers; keep a log of what you removed.
A20: Report the sample size and how people were found on the slide footnote.
A21: Show bad news honestly. Investors trust a number that sometimes fails a threshold.

Sheet Interview guide
A1: Interview guide (30-40 minutes)
A2: Use with survey respondents who ticked "OK to contact". Record with permission. Tag every quote with a hypothesis number.
A4: # | B4: Question or prompt | C4: What you are listening for | D4: Hypothesis
A5: 1 | B5: Walk me through the last time you bought or rented a property, from the first search to getting the keys. | C5: Steps, tools, time, who helped | D5: H1, H4
A6: 2 | B6: Where did you feel least in control or most worried? | C6: Fear points, trust gaps | D6: H2, H11
A7: 3 | B7: Tell me about a time a listing, price or promise turned out different from what you expected. | C7: Real stories of unavailable or misdescribed listings | D7: H2
A8: 4 | B8: What costs surprised you? | C8: Hidden fees, service charges, DLD fee | D8: H3
A9: 5 | B9: How did you keep track of documents, instalments and deadlines? | C9: Spreadsheet, memory, agent; any missed deadline | D9: H5a, H5b
A10: 6 | B10: What would you have paid to make it easier, and for which part? | C10: Willingness to pay, which step | D10: H6
A11: 7 | B11: How useful would it have been to walk through the exact unit in 3D before deciding? What else would you need? | C11: Real need for 3D vs nice to have | D11: H7
A12: 8 | B12: After getting the keys, how did you furnish or design the home? What was hard? | C12: Furniture and designer demand | D12: H10
A13: 9 | B13: Describe the idea in your own words after I explain it. What would make you trust it? What would stop you? | C13: Objections, trust, price | D13: H8
A14: 10 | B14: (UAE residents) If friends asked you about property, what would make you introduce them to a company for a fee? | C14: Referral appetite, concerns | D14: H9

Sheet Responses
A1: Responses: paste your survey export here
A2: Row 6 is an example and is NOT counted. Paste real answers from row 7 down, one row per respondent. Use the exact option wording from the Questionnaire sheet. Ratings are numbers 1 to 5.
A5: Respondent ID | B5: Date | C5: A1 Segment | D5: A2 Residence | E5: A5 Budget | F5: B3a Finding reliable information | G5: B3b Comparing options fairly | H5: B3c Checking that a listing, dev | I5: B3d Understanding the total cost | J5: B3e Paperwork and government reg | K5: B3f Arranging finance or payment | L5: B3g Tracking payments and deadli | M5: B3h Handover, snagging or move-i | N5: B3i Furnishing or designing the | O5: B4 Unavailable or misdescribed | P5: B5 Unexpected costs | Q5: B6 Weeks to complete | R5: B7 Price fair 1-5 | S5: B9 Agent satisfaction 1-5 | T5: B10 Delayed or gave up | U5: C2 Portal trust 1-5 | V5: C3 Pay for insights | W5: D1 3D importance 1-5 | X5: D2 3D lets me reserve | Y5: D3 Virtual design interest 1-5 | Z5: D4 Buy furniture in app | AA5: D5 Book designer in app | AB5: E3 Missed deadline | AC5: E4 Dashboard useful 1-5 | AD5: E5 Trust company with registrations 1-5 | AE5: F1 Likely to use 1-5 | AF5: F3 Acceptable fee | AG5: F5 Early access | AH5: G1 People asked advice | AI5: G3 Likely to refer 1-5 | AJ5: G6 Consider licence | AK5: H1 Interview OK
A6: EXAMPLE | B6: 2026-11-02 | C6: I plan to buy UAE property in the next 12 months | D6: Outside the UAE | E6: AED 1m-2m | F6: 4 | G6: 3 | H6: 5 | I6: 4 | J6: 4 | K6: 3 | L6: 4 | M6: 2 | N6: 3 | O6: Yes, once | P6: Yes | Q6: 16 | R6: 2 | S6: 3 | T6: Yes | U6: 3 | V6: Yes, one-off AED 50-150 | W6: 5 | X6: Yes | Y6: 4 | Z6: Probably | AA6: Not sure | AB6: No | AC6: 4 | AD6: 4 | AE6: 4 | AF6: 0.5-1% | AG6: Yes | AK6: Yes

Sheet Analysis
A1: Analysis: does the data prove the problem?
A2: Everything here is formula-driven from the Responses sheet. Blue cells are thresholds you can change before you look at the data.
A4: Sample
A5: Measure | B5: Value | C5: Note
A6: Total responses counted | B6: =COUNTA(Responses!$C$7:$C$1006) -> 0
A7: In the UAE | B7: =COUNTIF(Responses!$D$7:$D$1006,"In the UAE") -> 0
A8: Outside the UAE | B8: =COUNTIF(Responses!$D$7:$D$1006,"Outside the UAE") -> 0
A9: Minimum answers needed before a verdict | B9: 100 | C9: Planning assumption: 100 gives about +/-10% at 95% confidence.
A10: Margin of error at 95% confidence (all responses) | B10: =IFERROR(1.96*SQRT(0.25/B6),"") | C10: Worst case (50% result). Formula: 1.96 x square root of 0.25 / n.
A12: Hypotheses and proof
A13: ID | B13: Hypothesis | C13: Measure | D13: Pass if at least | E13: All | F13: In the UAE | G13: Outside the UAE | H13: Answered (n) | I13: Verdict | J13: Deck slide | K13: Statement for the deck
A14: H1 | B14: Finding reliable information is hard | C14: Rated 4-5 for "finding reliable information" | D14: 0.6 | E14: =IFERROR(COUNTIF(Responses!$F$7:$F$1006,">=4")/COUNT(Responses!$F$7:$F$1006),"") | F14: =IFERROR(COUNTIFS(Responses!$F$7:$F$1006,">=4",Responses!$D$7:$D$1006,"In the UAE")/COUNTIFS(Responses!$F$7:$F$1006,">=1",Responses!$D$7:$D$1006,"In the UAE"),"") | G14: =IFERROR(COUNTIFS(Responses!$F$7:$F$1006,">=4",Responses!$D$7:$D$1006,"Outside the UAE")/COUNTIFS(Responses!$F$7:$F$1006,">=1",Responses!$D$7:$D$1006,"Outside the UAE"),"") | H14: =COUNTA(Responses!$F$7:$F$1006) -> 0 | I14: =IF(H14<$B$9,"Need more responses",IF(E14="","No data",IF(E14>=D14,"Supported","Not supported"))) -> Need more responses | J14: 2 | K14: =IF(OR(E14="",H14<$B$9),"Not enough data yet","Of "&H14&" respondents, "&TEXT(E14,"0%")&" found it hard (4 or 5 out of 5) to find reliable information.") -> Not enough data yet
A15: H2 | B15: People meet unavailable or misdescribed listings | C15: Said yes to B4 (once or more) | D15: 0.5 | E15: =IFERROR((COUNTIF(Responses!$O$7:$O$1006,"Yes, more than once")+COUNTIF(Responses!$O$7:$O$1006,"Yes, once"))/COUNTA(Responses!$O$7:$O$1006),"") | F15: =IFERROR((COUNTIFS(Responses!$O$7:$O$1006,"Yes, more than once",Responses!$D$7:$D$1006,"In the UAE")+COUNTIFS(Responses!$O$7:$O$1006,"Yes, once",Responses!$D$7:$D$1006,"In the UAE"))/COUNTIFS(Responses!$O$7:$O$1006,"<>",Responses!$D$7:$D$1006,"In the UAE"),"") | G15: =IFERROR((COUNTIFS(Responses!$O$7:$O$1006,"Yes, more than once",Responses!$D$7:$D$1006,"Outside the UAE")+COUNTIFS(Responses!$O$7:$O$1006,"Yes, once",Responses!$D$7:$D$1006,"Outside the UAE"))/COUNTIFS(Responses!$O$7:$O$1006,"<>",Responses!$D$7:$D$1006,"Outside the UAE"),"") | H15: =COUNTA(Responses!$O$7:$O$1006) -> 0 | I15: =IF(H15<$B$9,"Need more responses",IF(E15="","No data",IF(E15>=D15,"Supported","Not supported"))) -> Need more responses | J15: 2 | K15: =IF(OR(E15="",H15<$B$9),"Not enough data yet","Of "&H15&" respondents, "&TEXT(E15,"0%")&" had contacted someone about a property that was already gone or not as described.") -> Not enough data yet
A16: H3 | B16: Unexpected costs are common | C16: Said yes to B5 | D16: 0.4 | E16: =IFERROR((COUNTIF(Responses!$P$7:$P$1006,"Yes"))/COUNTA(Responses!$P$7:$P$1006),"") | F16: =IFERROR((COUNTIFS(Responses!$P$7:$P$1006,"Yes",Responses!$D$7:$D$1006,"In the UAE"))/COUNTIFS(Responses!$P$7:$P$1006,"<>",Responses!$D$7:$D$1006,"In the UAE"),"") | G16: =IFERROR((COUNTIFS(Responses!$P$7:$P$1006,"Yes",Responses!$D$7:$D$1006,"Outside the UAE"))/COUNTIFS(Responses!$P$7:$P$1006,"<>",Responses!$D$7:$D$1006,"Outside the UAE"),"") | H16: =COUNTA(Responses!$P$7:$P$1006) -> 0 | I16: =IF(H16<$B$9,"Need more responses",IF(E16="","No data",IF(E16>=D16,"Supported","Not supported"))) -> Need more responses | J16: 2 | K16: =IF(OR(E16="",H16<$B$9),"Not enough data yet","Of "&H16&" respondents, "&TEXT(E16,"0%")&" faced costs they did not expect.") -> Not enough data yet
A17: H4 | B17: Paperwork and registrations are hard | C17: Rated 4-5 for "paperwork and registrations" | D17: 0.5 | E17: =IFERROR(COUNTIF(Responses!$J$7:$J$1006,">=4")/COUNT(Responses!$J$7:$J$1006),"") | F17: =IFERROR(COUNTIFS(Responses!$J$7:$J$1006,">=4",Responses!$D$7:$D$1006,"In the UAE")/COUNTIFS(Responses!$J$7:$J$1006,">=1",Responses!$D$7:$D$1006,"In the UAE"),"") | G17: =IFERROR(COUNTIFS(Responses!$J$7:$J$1006,">=4",Responses!$D$7:$D$1006,"Outside the UAE")/COUNTIFS(Responses!$J$7:$J$1006,">=1",Responses!$D$7:$D$1006,"Outside the UAE"),"") | H17: =COUNTA(Responses!$J$7:$J$1006) -> 0 | I17: =IF(H17<$B$9,"Need more responses",IF(E17="","No data",IF(E17>=D17,"Supported","Not supported"))) -> Need more responses | J17: 2 | K17: =IF(OR(E17="",H17<$B$9),"Not enough data yet","Of "&H17&" respondents, "&TEXT(E17,"0%")&" found paperwork and government registrations hard (4 or 5 out of 5).") -> Not enough data yet
A18: H4b | B18: Complexity makes people delay or give up | C18: Said yes to B10 | D18: 0.3 | E18: =IFERROR((COUNTIF(Responses!$T$7:$T$1006,"Yes"))/COUNTA(Responses!$T$7:$T$1006),"") | F18: =IFERROR((COUNTIFS(Responses!$T$7:$T$1006,"Yes",Responses!$D$7:$D$1006,"In the UAE"))/COUNTIFS(Responses!$T$7:$T$1006,"<>",Responses!$D$7:$D$1006,"In the UAE"),"") | G18: =IFERROR((COUNTIFS(Responses!$T$7:$T$1006,"Yes",Responses!$D$7:$D$1006,"Outside the UAE"))/COUNTIFS(Responses!$T$7:$T$1006,"<>",Responses!$D$7:$D$1006,"Outside the UAE"),"") | H18: =COUNTA(Responses!$T$7:$T$1006) -> 0 | I18: =IF(H18<$B$9,"Need more responses",IF(E18="","No data",IF(E18>=D18,"Supported","Not supported"))) -> Need more responses | J18: 2 | K18: =IF(OR(E18="",H18<$B$9),"Not enough data yet","Of "&H18&" respondents, "&TEXT(E18,"0%")&" had delayed or given up because it felt too complicated or risky.") -> Not enough data yet
A19: H5a | B19: Missed or late deadlines happen | C19: Said yes to E3 | D19: 0.25 | E19: =IFERROR((COUNTIF(Responses!$AB$7:$AB$1006,"Yes"))/COUNTA(Responses!$AB$7:$AB$1006),"") | F19: =IFERROR((COUNTIFS(Responses!$AB$7:$AB$1006,"Yes",Responses!$D$7:$D$1006,"In the UAE"))/COUNTIFS(Responses!$AB$7:$AB$1006,"<>",Responses!$D$7:$D$1006,"In the UAE"),"") | G19: =IFERROR((COUNTIFS(Responses!$AB$7:$AB$1006,"Yes",Responses!$D$7:$D$1006,"Outside the UAE"))/COUNTIFS(Responses!$AB$7:$AB$1006,"<>",Responses!$D$7:$D$1006,"Outside the UAE"),"") | H19: =COUNTA(Responses!$AB$7:$AB$1006) -> 0 | I19: =IF(H19<$B$9,"Need more responses",IF(E19="","No data",IF(E19>=D19,"Supported","Not supported"))) -> Need more responses | J19: 2 | K19: =IF(OR(E19="",H19<$B$9),"Not enough data yet","Of "&H19&" respondents, "&TEXT(E19,"0%")&" had missed or been late on a payment, registration or document deadline.") -> Not enough data yet
A20: H5b | B20: A single tracker is wanted | C20: Rated 4-5 for dashboard usefulness | D20: 0.6 | E20: =IFERROR(COUNTIF(Responses!$AC$7:$AC$1006,">=4")/COUNT(Responses!$AC$7:$AC$1006),"") | F20: =IFERROR(COUNTIFS(Responses!$AC$7:$AC$1006,">=4",Responses!$D$7:$D$1006,"In the UAE")/COUNTIFS(Responses!$AC$7:$AC$1006,">=1",Responses!$D$7:$D$1006,"In the UAE"),"") | G20: =IFERROR(COUNTIFS(Responses!$AC$7:$AC$1006,">=4",Responses!$D$7:$D$1006,"Outside the UAE")/COUNTIFS(Responses!$AC$7:$AC$1006,">=1",Responses!$D$7:$D$1006,"Outside the UAE"),"") | H20: =COUNTA(Responses!$AC$7:$AC$1006) -> 0 | I20: =IF(H20<$B$9,"Need more responses",IF(E20="","No data",IF(E20>=D20,"Supported","Not supported"))) -> Need more responses | J20: 6 | K20: =IF(OR(E20="",H20<$B$9),"Not enough data yet","Of "&H20&" respondents, "&TEXT(E20,"0%")&" said one dashboard for documents and payments would be very useful (4 or 5 out of 5).") -> Not enough data yet
A21: H6 | B21: People will pay for independent insights | C21: Chose any paid option in C3 | D21: 0.3 | E21: =IFERROR((COUNTA(Responses!$V$7:$V$1006)-COUNTIF(Responses!$V$7:$V$1006,"No, only if free"))/COUNTA(Responses!$V$7:$V$1006),"") | F21: =IFERROR((COUNTIFS(Responses!$V$7:$V$1006,"<>",Responses!$D$7:$D$1006,"In the UAE")-COUNTIFS(Responses!$V$7:$V$1006,"No, only if free",Responses!$D$7:$D$1006,"In the UAE"))/COUNTIFS(Responses!$V$7:$V$1006,"<>",Responses!$D$7:$D$1006,"In the UAE"),"") | G21: =IFERROR((COUNTIFS(Responses!$V$7:$V$1006,"<>",Responses!$D$7:$D$1006,"Outside the UAE")-COUNTIFS(Responses!$V$7:$V$1006,"No, only if free",Responses!$D$7:$D$1006,"Outside the UAE"))/COUNTIFS(Responses!$V$7:$V$1006,"<>",Responses!$D$7:$D$1006,"Outside the UAE"),"") | H21: =COUNTA(Responses!$V$7:$V$1006) -> 0 | I21: =IF(H21<$B$9,"Need more responses",IF(E21="","No data",IF(E21>=D21,"Supported","Not supported"))) -> Need more responses | J21: 7 | K21: =IF(OR(E21="",H21<$B$9),"Not enough data yet","Of "&H21&" respondents, "&TEXT(E21,"0%")&" would pay for independent insights.") -> Not enough data yet
A22: H7 | B22: 3D view of the exact unit matters | C22: Rated 4-5 for 3D importance | D22: 0.6 | E22: =IFERROR(COUNTIF(Responses!$W$7:$W$1006,">=4")/COUNT(Responses!$W$7:$W$1006),"") | F22: =IFERROR(COUNTIFS(Responses!$W$7:$W$1006,">=4",Responses!$D$7:$D$1006,"In the UAE")/COUNTIFS(Responses!$W$7:$W$1006,">=1",Responses!$D$7:$D$1006,"In the UAE"),"") | G22: =IFERROR(COUNTIFS(Responses!$W$7:$W$1006,">=4",Responses!$D$7:$D$1006,"Outside the UAE")/COUNTIFS(Responses!$W$7:$W$1006,">=1",Responses!$D$7:$D$1006,"Outside the UAE"),"") | H22: =COUNTA(Responses!$W$7:$W$1006) -> 0 | I22: =IF(H22<$B$9,"Need more responses",IF(E22="","No data",IF(E22>=D22,"Supported","Not supported"))) -> Need more responses | J22: 6 | K22: =IF(OR(E22="",H22<$B$9),"Not enough data yet","Of "&H22&" respondents, "&TEXT(E22,"0%")&" said a 3D walkthrough of the exact unit is important (4 or 5 out of 5).") -> Not enough data yet
A23: H8 | B23: The one-stop idea is attractive | C23: Rated 4-5 for likelihood to use | D23: 0.5 | E23: =IFERROR(COUNTIF(Responses!$AE$7:$AE$1006,">=4")/COUNT(Responses!$AE$7:$AE$1006),"") | F23: =IFERROR(COUNTIFS(Responses!$AE$7:$AE$1006,">=4",Responses!$D$7:$D$1006,"In the UAE")/COUNTIFS(Responses!$AE$7:$AE$1006,">=1",Responses!$D$7:$D$1006,"In the UAE"),"") | G23: =IFERROR(COUNTIFS(Responses!$AE$7:$AE$1006,">=4",Responses!$D$7:$D$1006,"Outside the UAE")/COUNTIFS(Responses!$AE$7:$AE$1006,">=1",Responses!$D$7:$D$1006,"Outside the UAE"),"") | H23: =COUNTA(Responses!$AE$7:$AE$1006) -> 0 | I23: =IF(H23<$B$9,"Need more responses",IF(E23="","No data",IF(E23>=D23,"Supported","Not supported"))) -> Need more responses | J23: 5 | K23: =IF(OR(E23="",H23<$B$9),"Not enough data yet","Of "&H23&" respondents, "&TEXT(E23,"0%")&" said they would likely use a one-stop app (4 or 5 out of 5).") -> Not enough data yet
A24: H9 | B24: UAE residents would refer others | C24: Rated 4-5 for likelihood to refer (UAE residents) | D24: 0.4 | E24: =IFERROR(COUNTIF(Responses!$AI$7:$AI$1006,">=4")/COUNT(Responses!$AI$7:$AI$1006),"") | F24: =IFERROR(COUNTIFS(Responses!$AI$7:$AI$1006,">=4",Responses!$D$7:$D$1006,"In the UAE")/COUNTIFS(Responses!$AI$7:$AI$1006,">=1",Responses!$D$7:$D$1006,"In the UAE"),"") | G24: =IFERROR(COUNTIFS(Responses!$AI$7:$AI$1006,">=4",Responses!$D$7:$D$1006,"Outside the UAE")/COUNTIFS(Responses!$AI$7:$AI$1006,">=1",Responses!$D$7:$D$1006,"Outside the UAE"),"") | H24: =COUNTA(Responses!$AI$7:$AI$1006) -> 0 | I24: =IF(H24<$B$9,"Need more responses",IF(E24="","No data",IF(E24>=D24,"Supported","Not supported"))) -> Need more responses | J24: 10 | K24: =IF(OR(E24="",H24<$B$9),"Not enough data yet","Of "&H24&" respondents, "&TEXT(E24,"0%")&" of UAE residents said they would likely refer a buyer for a fee (4 or 5 out of 5), concept test only.") -> Not enough data yet
A25: H10 | B25: Furniture and design add-on has demand | C25: Definitely or probably buy furniture in the app | D25: 0.4 | E25: =IFERROR((COUNTIF(Responses!$Z$7:$Z$1006,"Definitely")+COUNTIF(Responses!$Z$7:$Z$1006,"Probably"))/COUNTA(Responses!$Z$7:$Z$1006),"") | F25: =IFERROR((COUNTIFS(Responses!$Z$7:$Z$1006,"Definitely",Responses!$D$7:$D$1006,"In the UAE")+COUNTIFS(Responses!$Z$7:$Z$1006,"Probably",Responses!$D$7:$D$1006,"In the UAE"))/COUNTIFS(Responses!$Z$7:$Z$1006,"<>",Responses!$D$7:$D$1006,"In the UAE"),"") | G25: =IFERROR((COUNTIFS(Responses!$Z$7:$Z$1006,"Definitely",Responses!$D$7:$D$1006,"Outside the UAE")+COUNTIFS(Responses!$Z$7:$Z$1006,"Probably",Responses!$D$7:$D$1006,"Outside the UAE"))/COUNTIFS(Responses!$Z$7:$Z$1006,"<>",Responses!$D$7:$D$1006,"Outside the UAE"),"") | H25: =COUNTA(Responses!$Z$7:$Z$1006) -> 0 | I25: =IF(H25<$B$9,"Need more responses",IF(E25="","No data",IF(E25>=D25,"Supported","Not supported"))) -> Need more responses | J25: 7 | K25: =IF(OR(E25="",H25<$B$9),"Not enough data yet","Of "&H25&" respondents, "&TEXT(E25,"0%")&" would definitely or probably buy furniture through the same app.") -> Not enough data yet
A26: H11 | B26: Trust in portal data is low | C26: Rated 1-2 for trust in portals | D26: 0.25 | E26: =IFERROR(COUNTIF(Responses!$U$7:$U$1006,"<=2")/COUNT(Responses!$U$7:$U$1006),"") | F26: =IFERROR(COUNTIFS(Responses!$U$7:$U$1006,"<=2",Responses!$D$7:$D$1006,"In the UAE")/COUNTIFS(Responses!$U$7:$U$1006,">=1",Responses!$D$7:$D$1006,"In the UAE"),"") | G26: =IFERROR(COUNTIFS(Responses!$U$7:$U$1006,"<=2",Responses!$D$7:$D$1006,"Outside the UAE")/COUNTIFS(Responses!$U$7:$U$1006,">=1",Responses!$D$7:$D$1006,"Outside the UAE"),"") | H26: =COUNTA(Responses!$U$7:$U$1006) -> 0 | I26: =IF(H26<$B$9,"Need more responses",IF(E26="","No data",IF(E26>=D26,"Supported","Not supported"))) -> Need more responses | J26: 2 | K26: =IF(OR(E26="",H26<$B$9),"Not enough data yet","Of "&H26&" respondents, "&TEXT(E26,"0%")&" gave low trust (1 or 2 out of 5) to the information on property portals.") -> Not enough data yet
A27: H12 | B27: Price fairness is uncertain | C27: Rated 1-2 for confidence the price was fair | D27: 0.25 | E27: =IFERROR(COUNTIF(Responses!$R$7:$R$1006,"<=2")/COUNT(Responses!$R$7:$R$1006),"") | F27: =IFERROR(COUNTIFS(Responses!$R$7:$R$1006,"<=2",Responses!$D$7:$D$1006,"In the UAE")/COUNTIFS(Responses!$R$7:$R$1006,">=1",Responses!$D$7:$D$1006,"In the UAE"),"") | G27: =IFERROR(COUNTIFS(Responses!$R$7:$R$1006,"<=2",Responses!$D$7:$D$1006,"Outside the UAE")/COUNTIFS(Responses!$R$7:$R$1006,">=1",Responses!$D$7:$D$1006,"Outside the UAE"),"") | H27: =COUNTA(Responses!$R$7:$R$1006) -> 0 | I27: =IF(H27<$B$9,"Need more responses",IF(E27="","No data",IF(E27>=D27,"Supported","Not supported"))) -> Need more responses | J27: 2 | K27: =IF(OR(E27="",H27<$B$9),"Not enough data yet","Of "&H27&" respondents, "&TEXT(E27,"0%")&" were not confident the price or rent they agreed was fair (1 or 2 out of 5).") -> Not enough data yet
A28: Thresholds are suggestions set before looking at data. Agree them with your advisors first so the test is honest. A "Not supported" result is useful: change the pitch, not the threshold.
A29: Summary | B29: =COUNTIF(I14:I27,"Supported")&" of "&COUNTA(A14:A27)&" hypotheses supported" -> 0 of 14 hypotheses supported
A31: Where the journey hurts most
A32: Step | B32: Average difficulty (1-5) | C32: Rated 4-5 (%) | D32: Rank (1 = hardest) | E32: Answered (n)
A33: Finding reliable information on prices and areas | B33: =IFERROR(AVERAGE(Responses!$F$7:$F$1006),"") | C33: =IFERROR(COUNTIF(Responses!$F$7:$F$1006,">=4")/COUNT(Responses!$F$7:$F$1006),"") | D33: =IF(C33="","",RANK(C33,$C$33:$C$41)) | E33: =COUNT(Responses!$F$7:$F$1006) -> 0
A34: Comparing options fairly | B34: =IFERROR(AVERAGE(Responses!$G$7:$G$1006),"") | C34: =IFERROR(COUNTIF(Responses!$G$7:$G$1006,">=4")/COUNT(Responses!$G$7:$G$1006),"") | D34: =IF(C34="","",RANK(C34,$C$33:$C$41)) | E34: =COUNT(Responses!$G$7:$G$1006) -> 0
A35: Checking that a listing, developer or seller is genuine | B35: =IFERROR(AVERAGE(Responses!$H$7:$H$1006),"") | C35: =IFERROR(COUNTIF(Responses!$H$7:$H$1006,">=4")/COUNT(Responses!$H$7:$H$1006),"") | D35: =IF(C35="","",RANK(C35,$C$33:$C$41)) | E35: =COUNT(Responses!$H$7:$H$1006) -> 0
A36: Understanding the total cost including fees | B36: =IFERROR(AVERAGE(Responses!$I$7:$I$1006),"") | C36: =IFERROR(COUNTIF(Responses!$I$7:$I$1006,">=4")/COUNT(Responses!$I$7:$I$1006),"") | D36: =IF(C36="","",RANK(C36,$C$33:$C$41)) | E36: =COUNT(Responses!$I$7:$I$1006) -> 0
A37: Paperwork and government registrations | B37: =IFERROR(AVERAGE(Responses!$J$7:$J$1006),"") | C37: =IFERROR(COUNTIF(Responses!$J$7:$J$1006,">=4")/COUNT(Responses!$J$7:$J$1006),"") | D37: =IF(C37="","",RANK(C37,$C$33:$C$41)) | E37: =COUNT(Responses!$J$7:$J$1006) -> 0
A38: Arranging finance or payment | B38: =IFERROR(AVERAGE(Responses!$K$7:$K$1006),"") | C38: =IFERROR(COUNTIF(Responses!$K$7:$K$1006,">=4")/COUNT(Responses!$K$7:$K$1006),"") | D38: =IF(C38="","",RANK(C38,$C$33:$C$41)) | E38: =COUNT(Responses!$K$7:$K$1006) -> 0
A39: Tracking payments and deadlines | B39: =IFERROR(AVERAGE(Responses!$L$7:$L$1006),"") | C39: =IFERROR(COUNTIF(Responses!$L$7:$L$1006,">=4")/COUNT(Responses!$L$7:$L$1006),"") | D39: =IF(C39="","",RANK(C39,$C$33:$C$41)) | E39: =COUNT(Responses!$L$7:$L$1006) -> 0
A40: Handover, snagging or move-in | B40: =IFERROR(AVERAGE(Responses!$M$7:$M$1006),"") | C40: =IFERROR(COUNTIF(Responses!$M$7:$M$1006,">=4")/COUNT(Responses!$M$7:$M$1006),"") | D40: =IF(C40="","",RANK(C40,$C$33:$C$41)) | E40: =COUNT(Responses!$M$7:$M$1006) -> 0
A41: Furnishing or designing the home | B41: =IFERROR(AVERAGE(Responses!$N$7:$N$1006),"") | C41: =IFERROR(COUNTIF(Responses!$N$7:$N$1006,">=4")/COUNT(Responses!$N$7:$N$1006),"") | D41: =IF(C41="","",RANK(C41,$C$33:$C$41)) | E41: =COUNT(Responses!$N$7:$N$1006) -> 0
