Workbook
Name __bookmark_1: #REF!
Name _CAC22: #REF!
Name _DAT18: #REF!
Name _INC1: #REF!
Name _INC2: #REF!
Name _pnl94: #REF!
Name _SAL08: #REF!
Name a: #N/A
Name a1..318: #REF!
Name abc: #REF!
Name access: #REF!
Name AccountCodes: #REF!
Name AcqStkIncr: #REF!
Name Activation: #REF!
Name Admin_CleaningHO: #REF!
Name Admin_CleaningStores: #REF!
Name AdminCosts: #REF!
Name Adv.Mktg: #REF!
Name AIR_PAYM: #REF!
Name AIT: #REF!
Name ALL: #REF!
Name AMC_HRMS: #REF!
Name AMC_ORION: #REF!
Name amer: #REF!
Name Area: #REF!
Name asgasgd: word
Name asgasgd: word
Name asgd: word
Name asgd: word
Name assume: #REF!
Name ATIF3: word
Name ATIF3: word
Name AuditFeeSE: #REF!
Name Average_number_of_subs: #REF!
Name ayear: #REF!
Name b: #REF!
Name Bahrain_Conversion_Rate: #REF!
Name Balance_Sheet_CY_Date: #REF!
Name Balance_Sheet_PPY: #REF!
Name Balance_Sheet_PY_Date: #REF!
Name BankChargesBG: #REF!
Name BankChargesInterest: #REF!
Name BankChargesOther: #REF!
Name BankChargesTG: #REF!
Name beta: #REF!
Name Billing_2021: #REF!
Name Billing_Percent: #REF!
Name Bonus: #REF!
Name BS_1: #REF!
Name BS_2: #REF!
Name BS_Date_With_Prefix_001: #REF!
Name BSHEETALL: #REF!
Name bsk: #REF!
Name bsm: #REF!
Name BSRJ: #REF!
Name BSS: #REF!
Name BSU: #REF!
Name BusinessEntertainment: #REF!
Name CAC10S: #REF!
Name CAC10T: #REF!

Sheet Sheet1 (2)
B2: Circle Mall
B3: Start Date | C3: End Date | D3: Sales | E3: Rent | F3: Rent % | G3: Sqft | H3: Per sqft
B4: 44781 | C4: 45145 | D4: 3345376 | E4: =D4*F4 -> 468352.64 | F4: 0.14 | G4: 3598 | H4: =E4/G4 -> 130.17027
B5: 45146 | C5: 45511 | D5: 3476676 | E5: =D5*F5 -> 486734.64 | F5: 0.14 | G5: 3598 | H5: =E5/G5 -> 135.27922
B6: 45512 | C6: 45876 | D6: 3375376 | E6: =D6*F6 -> 472552.64 | F6: 0.14 | G6: 3598 | H6: =E6/G6 -> 131.33759
B7: 45877 | C7: 46241 | D7: =D10/10*12*95% -> 3778831 | E7: =D7*F7 -> 529036.33 | F7: 0.14 | G7: 3598 | H7: =E7/G7 -> 147.03622
H8: 246 | I8: 1 year | J8: Now
B10: YTD till May'26 | C10: 46173 | D10: 3314764
B11: Note :-

Sheet YR'26
C1: Adults - Circle Mall | K1: YTD | L1: Adults - Circle Mall | P1: FY | R1: Adults - Circle Mall
B2: Store code | D2: 46023 | E2: 46054 | F2: 46082 | G2: 46113 | H2: 46143 | I2: 46174 | J2: 46204 | K2: Ytd Bdgt | L2: % | M2: CY Ytd26 | N2: % | O2: %Bdgt | P2: FyBdgt | Q2: % | R2: FyEst | S2: % | T2: Variance | U2: Yr'25
C3: Sales | D3: 340704.6 | E3: 301035.14 | F3: 354918.32 | G3: 307390.56 | H3: 398212.2 | I3: 280658.37 | J3: 282307.7 | K3: 2278589.4 | L3: 1 | M3: 2265226.9 | N3: 1 | O3: 0.99413564 | P3: 4140734.4 | Q3: 1 | R3: 4474942.4 | S3: 1 | T3: 334208.03 | U3: 3635846.3 | V3: =R3-M3 -> 2209715.5
B4: Adults - Circle Mall | C4: Gross Margin | D4: 251335.78 | E4: 234082.59 | F4: 282025.76 | G4: 234518.88 | H4: 300033.88 | I4: 207023.74 | J4: 199392.36 | K4: 1767257.7 | L4: 0.7755929 | M4: 1708413 | N4: 0.75419067 | O4: 0.9667028 | P4: 3145859 | Q4: 0.75973455 | R4: 3344068.7 | S4: 0.74728755 | T4: 198209.76 | U4: 2505247.9 | V4: =R4-M4 -> 1635655.7
B5: Adults - Circle Mall | C5: Net Income | D5: 216529.82 | E5: 200693.9 | F5: 246333.41 | G5: 205198.53 | H5: 260494.34 | I5: 177127.62 | J5: 171177.67 | K5: 1455596.6 | L5: 0.6388148 | M5: 1477555.3 | N5: 0.65227695 | O5: 1.0150857 | P5: 2648975.9 | Q5: 0.63973577 | R5: 2893417.3 | S5: 0.64658202 | T5: 244441.39 | U5: 2235204.2 | V5: =R5-M5 -> 1415862
B6: Adults - Circle Mall | C6: emp.Exp | D6: 38194 | E6: 21006 | F6: 26813 | G6: 35147 | H6: 35978 | I6: 35568 | J6: 30329.4 | K6: 164207.19 | L6: 0.072065283 | M6: 223035.4 | N6: 0.098460512 | O6: 1.358256 | P6: 250665.73 | Q6: 0.060536539 | R6: 374682.4 | S6: 0.083728989 | T6: 124016.67 | U6: 246033.86 | V6: =R6-M6 -> 151647
B7: Adults - Circle Mall | C7: Rent | D7: 50814 | E7: 42341 | F7: 51528.1 | G7: 41359 | H7: 57361 | I7: 40999 | J7: 42206 | K7: 243430.72 | L7: 0.10683396 | M7: 326608.1 | N7: 0.14418339 | O7: 1.3416881 | P7: 660340.24 | Q7: 0.15947418 | R7: 743517.61 | S7: 0.16615133 | T7: 83177.378 | U7: 444170.54 | V7: =R7-M7 -> 416909.51
B8: Adults - Circle Mall | C8: Adv &Mktg Exp | D8: 4145 | E8: 5807 | F8: 9874 | G8: 10624 | H8: 9433 | I8: 11394 | J8: 6829 | K8: 16146.725 | L8: 0.0070862814 | M8: 58106 | N8: 0.025651294 | O8: 3.5986244 | P8: 88518.359 | Q8: 0.021377454 | R8: 89587.69 | S8: 0.020019853 | T8: 1069.3312 | U8: 33418.94 | V8: =R8-M8 -> 31481.69
B9: Adults - Circle Mall | C9: Other Admin | D9: 18782.11 | E9: 18680.49 | F9: 29851.889 | G9: 20022.141 | H9: 20979.71 | I9: 21560 | J9: 22156.22 | K9: 213809.26 | L9: 0.093834046 | M9: 152032.56 | N9: 0.06711582 | O9: 0.71106631 | P9: 329416.93 | Q9: 0.079555196 | R9: 262813.66 | S9: 0.058730066 | T9: -66603.273 | U9: 278611.63 | V9: =R9-M9 -> 110781.1
B10: Adults - Circle Mall | C10: Shared Cost Emp | D10: 13074 | E10: 14021.92 | F10: 13349.3 | G10: 18674 | H10: 22805 | I10: 23438 | J10: 19763 | K10: 214655.68 | L10: 0.094205511 | M10: 125125.22 | N10: 0.055237389 | O10: 0.58291131 | P10: 306096.57 | Q10: 0.073923258 | R10: 199668.52 | S10: 0.044619239 | T10: -106428.05 | U10: 83849.07 | V10: =R10-M10 -> 74543.305
B11: Adults - Circle Mall | C11: Shared Cost Others | D11: 14954 | E11: 11794 | F11: 6663 | G11: 7963 | H11: 5820 | I11: 6897 | J11: 6438 | K11: 16899.443 | L11: 0.0074166251 | M11: 60529 | N11: 0.026720944 | O11: 3.5817157 | P11: 47586.8 | Q11: 0.011492358 | R11: 91216.357 | S11: 0.020383806 | T11: 43629.557 | U11: 186106.41 | V11: =R11-M11 -> 30687.357
B12: Adults - Circle Mall | C12: Total Exp. | D12: 139963.11 | E12: 113650.41 | F12: 138079.29 | G12: 133789.14 | H12: 152376.71 | I12: 139856 | J12: 127721.62 | K12: 869149.01 | L12: 0.38144171 | M12: 945436.28 | N12: 0.41736935 | O12: 1.0877724 | P12: 1682624.6 | Q12: 0.40635899 | R12: 1761486.2 | S12: 0.39363328 | T12: 78861.615 | U12: 1272190.4 | V12: =R12-M12 -> 816049.96
B13: Adults - Circle Mall | C13: Store Profit | D13: 76566.71 | E13: 87043.49 | F13: 108254.12 | G13: 71409.389 | H13: 108117.63 | I13: 37271.62 | J13: 43456.05 | K13: 586447.59 | L13: 0.25737309 | M13: 532119.01 | N13: 0.2349076 | O13: 0.90735987 | P13: 966351.26 | Q13: 0.23337678 | R13: 1131931 | S13: 0.25294874 | T13: 165579.77 | U13: 963013.8 | V13: =R13-M13 -> 599812.02
B14: Adults - Circle Mall | C14: Depreciation | D14: 13948.123 | E14: 6455.0866 | F14: -617.67 | G14: -1453.23 | H14: -945.28 | I14: -1199.25 | J14: -973.8 | K14: 38603.249 | L14: 0.016941732 | M14: 15213.98 | N14: 0.0067163162 | O14: 0.39411139 | P14: 59292.287 | Q14: 0.014319268 | R14: 15213.98 | S14: 0.0033998158 | T14: -44078.307 | U14: 259318.77 | V14: =R14-M14 -> 0
B15: Adults - Circle Mall | C15: Finance & Extrdnry | D15: 190 | E15: 862 | F15: 1323.21 | G15: 509 | H15: 417 | I15: 239 | J15: 223 | K15: 6134.9517 | L15: 0.0026924341 | M15: 3763.21 | N15: 0.001661295 | O15: 0.61340499 | P15: 11049.998 | Q15: 0.0026686083 | R15: 4878.21 | S15: 0.0010901168 | T15: -6171.788 | U15: 0 | V15: =R15-M15 -> 1115
B16: Adults - Circle Mall | C16: Net Profit / Loss | D16: 62428.587 | E16: 79726.403 | F16: 107548.58 | G16: 72353.619 | H16: 108645.91 | I16: 38231.87 | J16: 44206.85 | K16: 541709.39 | L16: 0.23773893 | M16: 513141.82 | N16: 0.22652999 | O16: 0.94726403 | P16: 896008.98 | Q16: 0.21638891 | R16: 1111838.8 | S16: 0.24845881 | T16: 215829.86 | U16: 703695.03 | V16: =R16-M16 -> 598697.02

Sheet P & L
A1: Adults - Circle Mall | D1: Full Year Projection | L1: Jan to July -27 | N1: Year 2026 | U1: Full Year Projection 90%
A2: Adults | B2: Fy'25 | C2: % | D2: Yr'26 | E2: % | F2: Yr'27 -FY | G2: % | H2: Yr'28 | I2: % | J2: Yr'29 | K2: % | L2: Yr'27 - 7 MONTHS | M2: % | N2: Till July | P2: Aug to DEC | Q2: Remarks | R2: Remarks | U2: Yr'26
A3: Sales | B3: 3635846.3 | C3: 1 | D3: =N3+P3 -> 4474942.4 | E3: =D3/D$3 -> 1 | F3: =D3*1.02 -> 4564441.2 | G3: =F3/F$3 -> 1 | H3: =F3*1.02 -> 4655730.1 | I3: =H3/H$3 -> 1 | J3: =H3*1.02 -> 4748844.7 | K3: =J3/J$3 -> 1 | L3: =N3*1.02 -> 2310531.4 | M3: =L3/L$3 -> 1 | N3: ='YR''26'!M3 -> 2265226.9 | P3: 2209715.5 | U3: =N3+P3*90% -> 4253970.8
A4: Gross Margin | B4: 2505247.9 | C4: 0.68904121 | D4: =N4+P4 -> 3344068.7 | E4: =D4/D$3 -> 0.74728755 | F4: =F3*74% -> 3377686.5 | G4: =F4/F$3 -> 0.74 | H4: =H3*74% -> 3445240.2 | I4: =H4/H$3 -> 0.74 | J4: =J3*74% -> 3514145 | K4: =J4/J$3 -> 0.74 | L4: =N4*1.02 -> 1742581.2 | M4: =L4/L$3 -> 0.75419067 | N4: ='YR''26'!M4 -> 1708413 | P4: 1635655.7 | U4: =N4+P4*90% -> 3180503.1
A5: Net Income | B5: 2235204.2 | C5: 0.61476863 | D5: =N5+P5 -> 2893417.3 | E5: =D5/D$3 -> 0.64658202 | F5: =F3*64% -> 2921242.4 | G5: =F5/F$3 -> 0.64 | H5: =H3*64% -> 2979667.2 | I5: =H5/H$3 -> 0.64 | J5: =J3*64% -> 3039260.6 | K5: =J5/J$3 -> 0.64 | L5: =N5/N3*L3 -> 1507106.4 | M5: =L5/L$3 -> 0.65227695 | N5: ='YR''26'!M5 -> 1477555.3 | P5: 1415862 | U5: =U3*65% -> 2765081
A6: emp.Exp | B6: 246033.86 | C6: =B6/$B$3 -> 0.067668939 | D6: =N6+P6 -> 374682.4 | E6: =D6/D$3 -> 0.083728989 | F6: =D6*1.02 -> 382176.05 | G6: =F6/F$3 -> 0.083728989 | H6: =F6*1.02 -> 389819.57 | I6: =H6/H$3 -> 0.083728989 | J6: =H6*1.02 -> 397615.96 | K6: =J6/J$3 -> 0.083728989 | L6: =N6*1.02 -> 227496.11 | M6: =L6/L$3 -> 0.098460512 | N6: ='YR''26'!M6 -> 223035.4 | P6: 151647 | U6: =N6+P6 -> 374682.4
A7: Rent | B7: =B3*14% -> 509018.48 | C7: =B7/$B$3 -> 0.14 | D7: =N7+P7 -> 695403.1 | E7: =D7/D$3 -> 0.15539934 | F7: =F18 -> 885108 | G7: =F7/F$3 -> 0.19391377 | H7: =H18 -> 919289 | I7: =H7/H$3 -> 0.19745324 | J7: =J18 -> 955179.05 | K7: =J7/J$3 -> 0.20113925 | L7: =F7/12*7 -> 516313 | M7: =L7/L$3 -> 0.22346071 | N7: ='YR''26'!M7 -> 326608.1 | O7: =N7/N3 -> 0.14418339 | P7: =F18/12*5 -> 368795 | Q7: =P7/P3 -> 0.16689705 | R7: 7 month TOR & 5 Months FR | U7: =N7+P7 -> 695403.1
A8: Adv &mktng | B8: 33418.94 | C8: =B8/$B$3 -> 0.0091915162 | D8: =N8+P8 -> 89587.69 | E8: =D8/D$3 -> 0.020019853 | F8: =D8*1.02 -> 91379.444 | G8: =F8/F$3 -> 0.020019853 | H8: =F8*1.02 -> 93207.033 | I8: =H8/H$3 -> 0.020019853 | J8: =H8*1.02 -> 95071.173 | K8: =J8/J$3 -> 0.020019853 | L8: =N8*1.02 -> 59268.12 | M8: =L8/L$3 -> 0.025651294 | N8: ='YR''26'!M8 -> 58106 | P8: 31481.69 | U8: =N8+P8 -> 89587.69
A9: Othr Opex | B9: 278611.63 | C9: =B9/$B$3 -> 0.0766291 | D9: =N9+P9+2500*5 -> 275313.66 | E9: =D9/D$3 -> 0.061523398 | F9: =D9*1.02 -> 280819.93 | G9: =F9/F$3 -> 0.061523398 | H9: =F9*1.02 -> 286436.33 | I9: =H9/H$3 -> 0.061523398 | J9: =H9*1.02 -> 292165.06 | K9: =J9/J$3 -> 0.061523398 | L9: =N9*1.02 -> 155073.21 | M9: =L9/L$3 -> 0.06711582 | N9: ='YR''26'!M9 -> 152032.56 | P9: 110781.1 | U9: =N9+P9 -> 262813.66
A10: Shared Common | B10: 183849.07 | C10: =B10/$B$3 -> 0.050565688 | D10: =N10+P10 -> 199668.52 | E10: =D10/D$3 -> 0.044619239 | F10: =D10*1.02 -> 203661.9 | G10: =F10/F$3 -> 0.044619239 | H10: =F10*1.02 -> 207735.13 | I10: =H10/H$3 -> 0.044619239 | J10: =H10*1.02 -> 211889.84 | K10: =J10/J$3 -> 0.044619239 | L10: =N10*1.02 -> 127627.72 | M10: =L10/L$3 -> 0.055237389 | N10: ='YR''26'!M10 -> 125125.22 | P10: 74543.305 | U10: =N10+P10 -> 199668.52
A11: Shared Others | B11: 86106.41 | C11: =B11/$B$3 -> 0.023682632 | D11: =N11+P11 -> 91216.357 | E11: =D11/D$3 -> 0.020383806 | F11: =D11*1.02 -> 93040.684 | G11: =F11/F$3 -> 0.020383806 | H11: =F11*1.02 -> 94901.498 | I11: =H11/H$3 -> 0.020383806 | J11: =H11*1.02 -> 96799.528 | K11: =J11/J$3 -> 0.020383806 | L11: =N11*1.02 -> 61739.58 | M11: =L11/L$3 -> 0.026720944 | N11: ='YR''26'!M11 -> 60529 | P11: 30687.357 | U11: =N11+P11 -> 91216.357
A12: Total Exp. | B12: =SUM(B6:B11) -> 1337038.4 | C12: =B12/$B$3 -> 0.36773788 | D12: =SUM(D6:D11) -> 1725871.7 | E12: =D12/D$3 -> 0.38567463 | F12: =SUM(F6:F11) -> 1936186 | G12: =F12/F$3 -> 0.42418905 | H12: =SUM(H6:H11) -> 1991388.6 | I12: =H12/H$3 -> 0.42772853 | J12: =SUM(J6:J11) -> 2048720.6 | K12: =J12/J$3 -> 0.43141453 | L12: =SUM(L6:L11) -> 1147517.7 | M12: =L12/L$3 -> 0.49664667 | N12: ='YR''26'!M12 -> 945436.28 | P12: 816049.96 | U12: =SUM(U6:U11) -> 1713371.7
A13: Store Profit | B13: =B5-B12 -> 898165.86 | C13: =B13/$B$3 -> 0.24703076 | D13: =D5-D12 -> 1167545.5 | E13: =D13/D$3 -> 0.26090739 | F13: =F5-F12 -> 985056.38 | G13: =F13/F$3 -> 0.21581095 | H13: =H5-H12 -> 988278.67 | I13: =H13/H$3 -> 0.21227147 | J13: =J5-J12 -> 990539.97 | K13: =J13/J$3 -> 0.20858547 | L13: =L5-L12 -> 359588.65 | M13: =L13/L$3 -> 0.15563028 | N13: ='YR''26'!M13 -> 532119.01 | P13: 599812.02 | U13: =U5-U12 -> 1051709.3
A14: Depreciation | B14: 259318.77 | C14: =B14/$B$3 -> 0.071322809 | D14: =N14+P14 -> 15213.98 | E14: =D14/D$3 -> 0.0033998158 | F14: =D14 -> 15213.98 | G14: =F14/F$3 -> 0.0033331528 | I14: =H14/H$3 -> 0 | K14: =J14/J$3 -> 0 | L14: =P14 -> 0 | M14: =L14/L$3 -> 0 | N14: ='YR''26'!M14 -> 15213.98 | P14: 0 | U14: =N14+P14 -> 15213.98
A15: Finance Charges &Ext | B15: 0 | C15: =B15/$B$3 -> 0 | D15: =N15+P15 -> 4878.21 | E15: =D15/D$3 -> 0.0010901168 | F15: =D15 -> 4878.21 | G15: =F15/F$3 -> 0.001068742 | H15: 0 | I15: =H15/H$3 -> 0 | J15: 0 | K15: =J15/J$3 -> 0 | L15: =P15 -> 1115 | M15: =L15/L$3 -> 0.00048257296 | N15: ='YR''26'!M15 -> 3763.21 | P15: 1115 | U15: =N15+P15 -> 4878.21
A16: Net Profit / Loss | B16: =B13-B14 -> 638847.09 | C16: =B16/$B$3 -> 0.17570795 | D16: =D13-D14-D15 -> 1147453.4 | E16: =D16/D$3 -> 0.25641746 | F16: =F13-F14-F15 -> 964964.19 | G16: =F16/F$3 -> 0.21140905 | H16: =H13-H14 -> 988278.67 | I16: =H16/H$3 -> 0.21227147 | J16: =J13-J14 -> 990539.97 | K16: =J16/J$3 -> 0.20858547 | L16: =L13-L14-L15 -> 358473.65 | M16: =L16/L$3 -> 0.15514771 | N16: ='YR''26'!M16 -> 513141.82 | P16: 598697.02 | U16: =U13-U14-U15 -> 1031617.1
A17: Total Sqft | B17: 3598 | D17: 3598 | F17: 3598 | H17: 3598 | J17: 3598 | L17: 3598 | U17: 3598
A18: Rent | B18: =B7 -> 509018.48 | D18: =D7 -> 695403.1 | F18: =F17*F26 -> 885108 | H18: =H17*H26 -> 919289 | J18: =J17*J26 -> 955179.05 | L18: =L17*L26 -> 885108 | U18: 695403.1
A19: Per Sqft per annual | B19: =B18/B17 -> 141.47262 | D19: =D18/D17 -> 193.2749 | F19: =F18/F17 -> 246 | H19: =H18/H17 -> 255.5 | J19: =J18/J17 -> 265.475 | L19: =L18/L17 -> 246 | U19: 193.2749
A20: Per Sqft per month | B20: =B19/12 -> 11.789385 | D20: =D19/12 -> 16.106242 | F20: =F19/12 -> 20.5 | H20: =H19/12 -> 21.291667 | J20: =J19/12 -> 22.122917 | L20: =L19/12 -> 20.5 | U20: 16.106242
A21: Growth over TOR Vs Fixed Rent | F21: =F18/D18-1 -> 0.27279847 | H21: =H18/F18-1 -> 0.038617886 | J21: =J18/H18-1 -> 0.039041096
D22: =D19*1.2 -> 231.92988 | F22: =F18 -> 885108 | H22: =H18 -> 919289 | J22: =J18 -> 955179.05 | L22: =L18 -> 885108 | U22: 231.92988
A23: Base Rent | D23: 190 | F23: 190 | H23: =F23*1.05 -> 199.5 | J23: =H23*1.05 -> 209.475 | L23: 190 | U23: 190
A24: Sc/ Sq ft | D24: 41 | F24: 41 | H24: 41 | J24: 41 | L24: 41 | U24: 41
A25: MKT/Sqft | D25: 15 | F25: 15 | H25: 15 | J25: 15 | L25: 15 | U25: 15
D26: =SUM(D23:D25) -> 246 | F26: =SUM(F23:F25) -> 246 | H26: =SUM(H23:H25) -> 255.5 | J26: =SUM(J23:J25) -> 265.475 | L26: =SUM(L23:L25) -> 246 | U26: 246
A28: Year 2027 - Rent will change from Aug , if we renew and we have not considered

Sheet notes
A1: Since COTTON ON CIRCLE MALL is existing location, please find the Below rental benchmark for comparison.
A3: RENT
A4: Store Name | B4: Size (Sq.Ft) | C4: Base Rent | D4: SC/SqFt | E4: CW/SqFt | F4: MKT/SqFt | G4: Gross/SqFt
A5: Adults - Dubai Hills Mall | B5: 3,803.00 | C5: 244.00 | D5: 65.00 | E5: 20.00 | F5: 6.10 | G5: 335.10
A6: Adults - Dubai Mall | B6: 3,401.00 | C6: 365.00 | D6: 80.00 | E6: 20.00 | F6: 9.13 | G6: 474.13
A7: Adults-Mirdiff City Centre | B7: 6,757.00 | C7: 153.18 | D7: 69.81 | E7: 17.38 | F7: 21.41 | G7: 261.78
A8: Adults-Circle Mall | B8: 3,598.00 | C8: 190.00 | D8: 41.00 | E8: 15.00 | F8: - | G8: 246.00 | H8: Now
A10: Mall average annual footfall of approximately 7.5 million visitors.
A12: SALES
A14: 17-Feb-2022 to 07-Aug-2022 | B14: AED 1,750,345.97
A15: 08-Aug-2022 to 07-Aug-2023 | B15: AED 3,345,375.63
A16: 08-Aug-2023 to 07-Aug-2024 | B16: AED 3,476,676.14
A17: 08-Aug-2024 to 07-Aug-2025 | B17: AED 3,375,376.48
A18: 08-Aug-2025 to 07-Aug-2026 | B18: AED 3,936,735.19

Sheet P & L 5 Yrs
A1: Adults - Circle Mall | P1: g
A2: Adults | B2: Fy'25 | C2: % | D2: Yr'26 | E2: % | F2: Yr'27 -FY | G2: % | H2: Yr'28 | I2: % | J2: Yr'29 | K2: % | L2: Yr'30 | M2: % | N2: Yr'31 | O2: % | P2: Till July | Q2: Aug to DEC
A3: Sales | B3: 3635846.3 | C3: 1 | D3: =P3+Q3 -> 4474942.4 | E3: =D3/D$3 -> 1 | F3: =D3*1.02 -> 4564441.2 | G3: =F3/F$3 -> 1 | H3: =F3*1.02 -> 4655730.1 | I3: =H3/H$3 -> 1 | J3: =H3*1.02 -> 4748844.7 | K3: =J3/J$3 -> 1 | L3: =J3*1.02 -> 4843821.5 | M3: =L3/L$3 -> 1 | N3: =L3*1.02 -> 4940698 | O3: =N3/N$3 -> 1 | P3: ='YR''26'!M3 -> 2265226.9 | Q3: 2209715.5
A4: Gross Margin | B4: 2505247.9 | C4: 0.68904121 | D4: =P4+Q4 -> 3344068.7 | E4: =D4/D$3 -> 0.74728755 | F4: =F3*74% -> 3377686.5 | G4: =F4/F$3 -> 0.74 | H4: =H3*74% -> 3445240.2 | I4: =H4/H$3 -> 0.74 | J4: =J3*74% -> 3514145 | K4: =J4/J$3 -> 0.74 | L4: =L3*74% -> 3584427.9 | M4: =L4/L$3 -> 0.74 | N4: =N3*74% -> 3656116.5 | O4: =N4/N$3 -> 0.74 | P4: ='YR''26'!M4 -> 1708413 | Q4: 1635655.7
A5: Net Income | B5: 2235204.2 | C5: 0.61476863 | D5: =D3*64% -> 2863963.1 | E5: =D5/D$3 -> 0.64 | F5: =F3*64% -> 2921242.4 | G5: =F5/F$3 -> 0.64 | H5: =H3*64% -> 2979667.2 | I5: =H5/H$3 -> 0.64 | J5: =J3*64% -> 3039260.6 | K5: =J5/J$3 -> 0.64 | L5: =L3*64% -> 3100045.8 | M5: =L5/L$3 -> 0.64 | N5: =N3*64% -> 3162046.7 | O5: =N5/N$3 -> 0.64 | P5: ='YR''26'!M5 -> 1477555.3 | Q5: 1415862
A6: emp.Exp | B6: 246033.86 | C6: =B6/$B$3 -> 0.067668939 | D6: =P6+Q6 -> 374682.4 | E6: =D6/D$3 -> 0.083728989 | F6: =D6*1.02 -> 382176.05 | G6: =F6/F$3 -> 0.083728989 | H6: =F6*1.02 -> 389819.57 | I6: =H6/H$3 -> 0.083728989 | J6: =H6*1.02 -> 397615.96 | K6: =J6/J$3 -> 0.083728989 | L6: =J6*1.02 -> 405568.28 | M6: =L6/L$3 -> 0.083728989 | N6: =L6*1.02 -> 413679.65 | O6: =N6/N$3 -> 0.083728989 | P6: ='YR''26'!M6 -> 223035.4 | Q6: 151647
A7: Rent | B7: 444170.54 | C7: =B7/$B$3 -> 0.12216428 | D7: =P7+Q7 -> 695403.1 | E7: =D7/D$3 -> 0.15539934 | F7: =F18 -> 885108 | G7: =F7/F$3 -> 0.19391377 | H7: =H18 -> 919289 | I7: =H7/H$3 -> 0.19745324 | J7: =J18 -> 955179.05 | K7: =J7/J$3 -> 0.20113925 | L7: =L18 -> 992863.6 | M7: =L7/L$3 -> 0.20497526 | N7: =N18 -> 1032432.4 | O7: =N7/N$3 -> 0.20896488 | P7: ='YR''26'!M7 -> 326608.1 | Q7: =F18/12*5 -> 368795
A8: Adv &mktng | B8: 33418.94 | C8: =B8/$B$3 -> 0.0091915162 | D8: =P8+Q8 -> 89587.69 | E8: =D8/D$3 -> 0.020019853 | F8: =D8*1.02 -> 91379.444 | G8: =F8/F$3 -> 0.020019853 | H8: =F8*1.02 -> 93207.033 | I8: =H8/H$3 -> 0.020019853 | J8: =H8*1.02 -> 95071.173 | K8: =J8/J$3 -> 0.020019853 | L8: =J8*1.02 -> 96972.597 | M8: =L8/L$3 -> 0.020019853 | N8: =L8*1.02 -> 98912.049 | O8: =N8/N$3 -> 0.020019853 | P8: ='YR''26'!M8 -> 58106 | Q8: 31481.69
A9: Othr Opex | B9: 278611.63 | C9: =B9/$B$3 -> 0.0766291 | D9: =P9+Q9+2500*5 -> 275313.66 | E9: =D9/D$3 -> 0.061523398 | F9: =D9*1.02 -> 280819.93 | G9: =F9/F$3 -> 0.061523398 | H9: =F9*1.02 -> 286436.33 | I9: =H9/H$3 -> 0.061523398 | J9: =H9*1.02 -> 292165.06 | K9: =J9/J$3 -> 0.061523398 | L9: =J9*1.02 -> 298008.36 | M9: =L9/L$3 -> 0.061523398 | N9: =L9*1.02 -> 303968.53 | O9: =N9/N$3 -> 0.061523398 | P9: ='YR''26'!M9 -> 152032.56 | Q9: 110781.1
A10: Shared Common | B10: 183849.07 | C10: =B10/$B$3 -> 0.050565688 | D10: =P10+Q10 -> 199668.52 | E10: =D10/D$3 -> 0.044619239 | F10: =D10*1.02 -> 203661.9 | G10: =F10/F$3 -> 0.044619239 | H10: =F10*1.02 -> 207735.13 | I10: =H10/H$3 -> 0.044619239 | J10: =H10*1.02 -> 211889.84 | K10: =J10/J$3 -> 0.044619239 | L10: =J10*1.02 -> 216127.63 | M10: =L10/L$3 -> 0.044619239 | N10: =L10*1.02 -> 220450.18 | O10: =N10/N$3 -> 0.044619239 | P10: ='YR''26'!M10 -> 125125.22 | Q10: 74543.305
A11: Shared Others | B11: 86106.41 | C11: =B11/$B$3 -> 0.023682632 | D11: =P11+Q11 -> 91216.357 | E11: =D11/D$3 -> 0.020383806 | F11: =D11*1.02 -> 93040.684 | G11: =F11/F$3 -> 0.020383806 | H11: =F11*1.02 -> 94901.498 | I11: =H11/H$3 -> 0.020383806 | J11: =H11*1.02 -> 96799.528 | K11: =J11/J$3 -> 0.020383806 | L11: =J11*1.02 -> 98735.518 | M11: =L11/L$3 -> 0.020383806 | N11: =L11*1.02 -> 100710.23 | O11: =N11/N$3 -> 0.020383806 | P11: ='YR''26'!M11 -> 60529 | Q11: 30687.357
A12: Total Exp. | B12: =SUM(B6:B11) -> 1272190.4 | C12: =B12/$B$3 -> 0.34990215 | D12: =SUM(D6:D11) -> 1725871.7 | E12: =D12/D$3 -> 0.38567463 | F12: =SUM(F6:F11) -> 1936186 | G12: =F12/F$3 -> 0.42418905 | H12: =SUM(H6:H11) -> 1991388.6 | I12: =H12/H$3 -> 0.42772853 | J12: =SUM(J6:J11) -> 2048720.6 | K12: =J12/J$3 -> 0.43141453 | L12: =SUM(L6:L11) -> 2108276 | M12: =L12/L$3 -> 0.43525055 | N12: =SUM(N6:N11) -> 2170153 | O12: =N12/N$3 -> 0.43924017 | P12: ='YR''26'!M12 -> 945436.28 | Q12: 816049.96
A13: Store Profit | B13: =B5-B12 -> 963013.8 | C13: =B13/$B$3 -> 0.26486648 | D13: =D5-D12 -> 1138091.4 | E13: =D13/D$3 -> 0.25432537 | F13: =F5-F12 -> 985056.38 | G13: =F13/F$3 -> 0.21581095 | H13: =H5-H12 -> 988278.67 | I13: =H13/H$3 -> 0.21227147 | J13: =J5-J12 -> 990539.97 | K13: =J13/J$3 -> 0.20858547 | L13: =L5-L12 -> 991769.8 | M13: =L13/L$3 -> 0.20474945 | N13: =N5-N12 -> 991893.69 | O13: =N13/N$3 -> 0.20075983 | P13: ='YR''26'!M13 -> 532119.01 | Q13: 599812.02
A14: Depreciation | B14: 259318.77 | C14: =B14/$B$3 -> 0.071322809 | D14: =P14+Q14 -> 15213.98 | E14: =D14/D$3 -> 0.0033998158 | F14: =D14 -> 15213.98 | G14: =F14/F$3 -> 0.0033331528 | I14: =H14/H$3 -> 0 | K14: =J14/J$3 -> 0 | M14: =L14/L$3 -> 0 | O14: =N14/N$3 -> 0 | P14: ='YR''26'!M14 -> 15213.98 | Q14: 0
A15: Finance Charges &Ext | B15: 0 | C15: =B15/$B$3 -> 0 | D15: =P15+Q15 -> 4878.21 | E15: =D15/D$3 -> 0.0010901168 | F15: =D15 -> 4878.21 | G15: =F15/F$3 -> 0.001068742 | H15: 0 | I15: =H15/H$3 -> 0 | J15: 0 | K15: =J15/J$3 -> 0 | L15: 0 | M15: =L15/L$3 -> 0 | N15: 0 | O15: =N15/N$3 -> 0 | P15: ='YR''26'!M15 -> 3763.21 | Q15: 1115
A16: Net Profit / Loss | B16: =B13-B14 -> 703695.03 | C16: =B16/$B$3 -> 0.19354367 | D16: =D13-D14-D15 -> 1117999.2 | E16: =D16/D$3 -> 0.24983544 | F16: =F13-F14-F15 -> 964964.19 | G16: =F16/F$3 -> 0.21140905 | H16: =H13-H14 -> 988278.67 | I16: =H16/H$3 -> 0.21227147 | J16: =J13-J14 -> 990539.97 | K16: =J16/J$3 -> 0.20858547 | L16: =L13-L14 -> 991769.8 | M16: =L16/L$3 -> 0.20474945 | N16: =N13-N14 -> 991893.69 | O16: =N16/N$3 -> 0.20075983 | P16: ='YR''26'!M16 -> 513141.82 | Q16: 598697.02
A17: Total Sqft | B17: 3598 | D17: 3598 | F17: 3598 | H17: 3598 | J17: 3598 | L17: 3598 | N17: 3598
A18: Rent | B18: =B7 -> 444170.54 | D18: =D7 -> 695403.1 | F18: =F17*F26 -> 885108 | H18: =H17*H26 -> 919289 | J18: =J17*J26 -> 955179.05 | L18: =L17*L26 -> 992863.6 | N18: =N17*N26 -> 1032432.4
A19: Per Sqft per annual | B19: =B18/B17 -> 123.44929 | D19: =D18/D17 -> 193.2749 | F19: =F18/F17 -> 246 | H19: =H18/H17 -> 255.5 | J19: =J18/J17 -> 265.475 | L19: =L18/L17 -> 275.94875 | N19: =N18/N17 -> 286.94619
A20: Per Sqft per month | B20: =B19/12 -> 10.287441 | D20: =D19/12 -> 16.106242 | F20: =F19/12 -> 20.5 | H20: =H19/12 -> 21.291667 | J20: =J19/12 -> 22.122917 | L20: =L19/12 -> 22.995729 | N20: =N19/12 -> 23.912182
A21: Growth over TOR Vs Fixed Rent | F21: =F18/D18-1 -> 0.27279847 | H21: =H18/F18-1 -> 0.038617886 | J21: =J18/H18-1 -> 0.039041096 | L21: =L18/J18-1 -> 0.039452868 | N21: =N18/L18-1 -> 0.039853188
D22: =D19*1.2 -> 231.92988 | F22: =F18 -> 885108 | H22: =H18 -> 919289 | J22: =J18 -> 955179.05 | L22: =L18 -> 992863.6 | N22: =N18 -> 1032432.4
A23: Base Rent | D23: 190 | F23: 190 | H23: =F23*1.05 -> 199.5 | J23: =H23*1.05 -> 209.475 | L23: =J23*1.05 -> 219.94875 | N23: =L23*1.05 -> 230.94619
A24: Sc/ Sq ft | D24: 41 | F24: 41 | H24: 41 | J24: 41 | L24: 41 | N24: 41
A25: MKT/Sqft | D25: 15 | F25: 15 | H25: 15 | J25: 15 | L25: 15 | N25: 15
D26: =SUM(D23:D25) -> 246 | F26: =SUM(F23:F25) -> 246 | H26: =SUM(H23:H25) -> 255.5 | J26: =SUM(J23:J25) -> 265.475 | L26: =SUM(L23:L25) -> 275.94875 | N26: =SUM(N23:N25) -> 286.94619
A28: Year 2027 - Rent will change from Aug , if we renew and we have not considered

Sheet Scenario
B2: Scenarion 1 | C2: Revise Rent
B3: Scenarion 2 | C3: Revise Rent & Capex Renovation within 3 years and consider renovation 5th Year ( as per the mall instruction ) - The current capex invested by Mall Management Capex amount AED 2 Mn with 5 year depreciation
B5: Rent options
C7: Start | D7: End | E7: Size (Sq.Ft) | F7: Base Rent | G7: SC/SqFt | H7: MKT/SqFt | I7: Gross Rent Per SqFt | J7: Gross Rent | K7: TOR%
B8: Adults - Circle Mall | C8: 46242 | D8: 46606 | E8: 3598 | F8: 240 | G8: 41 | H8: 15 | I8: 296 | J8: =I8*E8 -> 1065008 | K8: 0.12
B9: Adults - Circle Mall | C9: 46607 | D9: 46972 | E9: 3598 | F9: 252 | G9: 41 | H9: 15 | I9: 308 | J9: =I9*E9 -> 1108184 | K9: 0.12
B10: Adults - Circle Mall | C10: 46973 | D10: 47337 | E10: 3598 | F10: 264.6 | G10: 42.02 | H10: 15 | I10: 321.62 | J10: =I10*E10 -> 1157188.8 | K10: 0.12
C12: Start | D12: End | E12: Size (Sq.Ft) | F12: Base Rent | G12: SC/SqFt | H12: MKT/SqFt | I12: Gross Rent Per SqFt | J12: Gross Rent | K12: TOR%
B13: Adults - Circle Mall | C13: 46242 | D13: 46606 | E13: 3598 | F13: 200 | G13: 41 | H13: 15 | I13: =F13+G13+H13 -> 256 | J13: =I13*E13 -> 921088 | K13: 0.12
B14: Adults - Circle Mall | C14: 46607 | D14: 46972 | E14: 3598 | F14: =F13*1.05 -> 210 | G14: 41 | H14: 15 | I14: =F14+G14+H14 -> 266 | J14: =I14*E14 -> 957068 | K14: 0.12
B15: Adults - Circle Mall | C15: 46973 | D15: 47337 | E15: 3598 | F15: =F14*1.05 -> 220.5 | G15: 42.02 | H15: 15 | I15: =F15+G15+H15 -> 277.52 | J15: =I15*E15 -> 998516.96 | K15: 0.12
C18: Start | D18: End | E18: Size (Sq.Ft) | F18: Base Rent | G18: SC/SqFt | H18: MKT/SqFt | I18: Gross Rent Per SqFt | J18: Gross Rent | K18: TOR%
B19: Adults - Circle Mall | C19: 46242 | D19: 46606 | E19: 3598 | F19: 180 | G19: 41 | H19: 15 | I19: =F19+G19+H19 -> 236 | J19: =I19*E19 -> 849128 | K19: 0.12
B20: Adults - Circle Mall | C20: 46607 | D20: 46972 | E20: 3598 | F20: =F19*1.05 -> 189 | G20: 41 | H20: 15 | I20: =F20+G20+H20 -> 245 | J20: =I20*E20 -> 881510 | K20: 0.12
B21: Adults - Circle Mall | C21: 46973 | D21: 47337 | E21: 3598 | F21: =F20*1.05 -> 198.45 | G21: 42.02 | H21: 15 | I21: =F21+G21+H21 -> 255.47 | J21: =I21*E21 -> 919181.06 | K21: 0.12
C23: Start | D23: End | E23: Size (Sq.Ft) | F23: Base Rent | G23: SC/SqFt | H23: MKT/SqFt | I23: Gross Rent Per SqFt | J23: Gross Rent | K23: TOR%
B24: Adults - Circle Mall | C24: 46242 | D24: 46606 | E24: 3598 | F24: 170 | G24: 41 | H24: 15 | I24: =F24+G24+H24 -> 226 | J24: =I24*E24 -> 813148 | K24: 0.12
B25: Adults - Circle Mall | C25: 46607 | D25: 46972 | E25: 3598 | F25: =F24*1.05 -> 178.5 | G25: 41 | H25: 15 | I25: =F25+G25+H25 -> 234.5 | J25: =I25*E25 -> 843731 | K25: 0.12
B26: Adults - Circle Mall | C26: 46973 | D26: 47337 | E26: 3598 | F26: =F25*1.05 -> 187.425 | G26: 42.02 | H26: 15 | I26: =F26+G26+H26 -> 244.445 | J26: =I26*E26 -> 879513.11 | K26: 0.12

Sheet Circle Mall Rent
A1: Store Name
B2: Start | C2: End | D2: Size (Sq.Ft) | E2: Base Rent | F2: SC/SqFt | G2: MKT/SqFt | H2: Gross Rent Per SqFt | I2: Gross Rent | J2: TOR%
A3: Adults - Circle Mall | B3: 46242 | C3: 46606 | D3: 3598 | E3: 240 | F3: 41 | G3: 15 | H3: 296 | I3: =H3*D3 -> 1065008 | J3: 0.12
A4: Adults - Circle Mall | B4: 46607 | C4: 46972 | D4: 3598 | E4: 252 | F4: 41 | G4: 15 | H4: 308 | I4: =H4*D4 -> 1108184 | J4: 0.12
A5: Adults - Circle Mall | B5: 46973 | C5: 47337 | D5: 3598 | E5: 264.6 | F5: 42.02 | G5: 15 | H5: 321.62 | I5: =H5*D5 -> 1157188.8 | J5: 0.12
B7: Start | C7: End | D7: Size (Sq.Ft) | E7: Base Rent | F7: SC/SqFt | G7: MKT/SqFt | H7: Gross Rent Per SqFt | I7: Gross Rent | J7: TOR%
A8: Adults - Circle Mall | B8: 46242 | C8: 46606 | D8: 3598 | E8: 200 | F8: 41 | G8: 15 | H8: =E8+F8+G8 -> 256 | I8: =H8*D8 -> 921088 | J8: 0.12
A9: Adults - Circle Mall | B9: 46607 | C9: 46972 | D9: 3598 | E9: =E8*1.05 -> 210 | F9: 41 | G9: 15 | H9: =E9+F9+G9 -> 266 | I9: =H9*D9 -> 957068 | J9: 0.12
A10: Adults - Circle Mall | B10: 46973 | C10: 47337 | D10: 3598 | E10: =E9*1.05 -> 220.5 | F10: 42.02 | G10: 15 | H10: =E10+F10+G10 -> 277.52 | I10: =H10*D10 -> 998516.96 | J10: 0.12
B13: Start | C13: End | D13: Size (Sq.Ft) | E13: Base Rent | F13: SC/SqFt | G13: MKT/SqFt | H13: Gross Rent Per SqFt | I13: Gross Rent | J13: TOR%
A14: Adults - Circle Mall | B14: 46242 | C14: 46606 | D14: 3598 | E14: 180 | F14: 41 | G14: 15 | H14: =E14+F14+G14 -> 236 | I14: =H14*D14 -> 849128 | J14: 0.12
A15: Adults - Circle Mall | B15: 46607 | C15: 46972 | D15: 3598 | E15: =E14*1.05 -> 189 | F15: 41 | G15: 15 | H15: =E15+F15+G15 -> 245 | I15: =H15*D15 -> 881510 | J15: 0.12
A16: Adults - Circle Mall | B16: 46973 | C16: 47337 | D16: 3598 | E16: =E15*1.05 -> 198.45 | F16: 42.02 | G16: 15 | H16: =E16+F16+G16 -> 255.47 | I16: =H16*D16 -> 919181.06 | J16: 0.12
B18: Start | C18: End | D18: Size (Sq.Ft) | E18: Base Rent | F18: SC/SqFt | G18: MKT/SqFt | H18: Gross Rent Per SqFt | I18: Gross Rent | J18: TOR%
A19: Adults - Circle Mall | B19: 46242 | C19: 46606 | D19: 3598 | E19: 170 | F19: 41 | G19: 15 | H19: =E19+F19+G19 -> 226 | I19: =H19*D19 -> 813148 | J19: 0.12
A20: Adults - Circle Mall | B20: 46607 | C20: 46972 | D20: 3598 | E20: =E19*1.05 -> 178.5 | F20: 41 | G20: 15 | H20: =E20+F20+G20 -> 234.5 | I20: =H20*D20 -> 843731 | J20: 0.12
A21: Adults - Circle Mall | B21: 46973 | C21: 47337 | D21: 3598 | E21: =E20*1.05 -> 187.425 | F21: 42.02 | G21: 15 | H21: =E21+F21+G21 -> 244.445 | I21: =H21*D21 -> 879513.11 | J21: 0.12
